wretched_tower/__init__.py
wretched_tower/app.py
wretched_tower/py.typed
wretched_tower/tower.py
wretched_tower-0.1.2.dist-info/METADATA
wretched_tower-0.1.2.dist-info/WHEEL
wretched_tower-0.1.2.dist-info/entry_points.txt
wretched_tower-0.1.2.dist-info/licenses/LICENSE
wretched_tower-0.1.2.dist-info/RECORD
