Metadata-Version: 2.4
Name: wretched-tower
Version: 0.1.2
Summary: A digital die rolling tools for use as an alternative tool for games that implement a tumbling tower resolution mechanic such as those based on the Wretched and Alone SRD.
Project-URL: Repository, https://codeberg.org/andrlik/wretched-tower
Project-URL: Homepage, https://codeberg.org/andrlik/wretched-tower
Project-URL: Documentation, https://wretched-tower.readthedocs.io/en/latest/
Author-email: Daniel Andrlik <daniel@andrlik.org>
License-File: LICENSE
Classifier: Development Status :: 2 - Pre-Alpha
Classifier: License :: OSI Approved :: BSD License
Classifier: Programming Language :: Python :: 3.12
Classifier: Programming Language :: Python :: 3.13
Classifier: Programming Language :: Python :: 3.14
Requires-Python: >=3.12
Requires-Dist: textual>=2.1.2
